MANIFEST.in
README.txt
bootstrap.py
buildout.cfg
setup.py
docs/HISTORY.txt
esteele/__init__.py
esteele.manager.egg-info/PKG-INFO
esteele.manager.egg-info/SOURCES.txt
esteele.manager.egg-info/dependency_links.txt
esteele.manager.egg-info/entry_points.txt
esteele.manager.egg-info/namespace_packages.txt
esteele.manager.egg-info/not-zip-safe
esteele.manager.egg-info/requires.txt
esteele.manager.egg-info/top_level.txt
esteele/manager/__init__.py
esteele/manager/buildout.py
esteele/manager/changelog.py
esteele/manager/db.py
esteele/manager/manage.py
esteele/manager/pypi.py
esteele/manager/release.py