Metadata-Version: 1.1
Name: esteele.manager
Version: 1.1
Summary: Plone release management utilities
Home-page: https://github.com/plone/esteele.manager
Author: Eric Steele
Author-email: eric@esteele.net
License: GPL
Keywords: plone release
Platform: UNKNOWN
Classifier: Programming Language :: Python
Classifier: Framework :: Plone
Classifier: Programming Language :: Python :: 2.7
